_hdf5_udf.py
hdf5_udf.py
hdf5_udf_resources/__init__.py
hdf5_udf_resources/hdf5_udf-schema.json
PyHDF5_UDF-1.3.dist-info/LICENSE.txt
PyHDF5_UDF-1.3.dist-info/METADATA
PyHDF5_UDF-1.3.dist-info/WHEEL
PyHDF5_UDF-1.3.dist-info/top_level.txt
PyHDF5_UDF-1.3.dist-info/RECORD
