Metadata-Version: 2.1
Name: PyHDF5-UDF
Version: 1.3
Summary: User-defined functions for HDF5 - Python bindings
Home-page: https://hdf5-udf.readthedocs.io
Author: Lucas C. Villa Real
Author-email: lucasvr@gobolinux.org
License: UNKNOWN
Platform: UNKNOWN
Requires-Python: >=3.5.10
Requires-Dist: cffi (>=1.0.0)
Requires-Dist: jsonschema (>=3.2.0)
